{
    "a": -6.06e-4, 
    "b": 0.9182, 
    "c": 0, 
    "n": 1, 
    "C": 6.38e-4, 
    "aSAT": 0.01, 
    "bSAT": 0.4927, 
    "cSAT": 10.48, 
    "dSAT": 0.2588, 
    "aSF": 50, 
    "bSF": 0.5, 
    "klambda": 6.815, 
    "g": 9.81, 
    "CPB": 50, 
    "Pe": 0.15, 
    "hT": 0.48, 
    "kv": 1e-3, 
    "f": 0.8, 
    "K": 5, 
    "Llip": 1.51, 
    "hover": 0.15, 
    "freq_bubble_size": [500, 1300, 1700, 2000, 1200], 
    "db_k_pulp": [2e-4, 4e-4, 6e-4, 8e-4, 1e-3], 
    "epsis": [0.18, 0.16, 0.14, 0.12, 0.1], 
    "Cfeed": [0.2, 0.8], 
    "Qfeed":1.67e-4, 
    "P": [2.8e-4, 3e-4], 
    "dp": [75e-6, 73e-6], 
    "Vcell": 0.087, 
    "Acell": 0.18,
    "phi": 0.2, 
    "density_sol": 2500, 
    "density_water": 1000, 
    "viscosity_water": 1e-3 
}